[ 
    {
    "name": "UMMA",
    "website": "https://ummalife.com/",
    "description": "One Ummah — One Network.",
    "explorer": "https://polygonscan.com/token/0x36596A1dC57c695Bed1A063470a7802797Dca133",
    "logo": "https://raw.githubusercontent.com/ISLAMIBLOCKCHAIN/ISLAMIwallet/main/Coins/Logo/UMMA.png",    
    "type": "POLYGON",
    "symbol": "UMMA",
    "decimals": 18,
    "status": "active",
    "price": 0.001,
    "priceChangePercentage24h":3.22,
    "id": "0x36596A1dC57c695Bed1A063470a7802797Dca133"
 },
    {
    "name": "Coinerr",
    "website": "https://coinerr.io",
    "description": "Coinerr make your payments easierr, make your world betterr, make your shopping saferr.",
    "explorer": "https://polygonscan.com/token/0xfb32513135e3267995268e3099d2b6114d20b6ed",
    "logo": "https://raw.githubusercontent.com/ISLAMIBLOCKCHAIN/ISLAMIwallet/main/Coins/Logo/ERR.png",    
    "type": "POLYGON",
    "symbol": "ERR",
    "decimals": 9,
    "status": "active",
    "price": 0.11,
    "priceChangePercentage24h":1.22,
    "id": "0xFB32513135e3267995268E3099d2B6114d20B6eD",
    "links": [
        {
            "name": "twitter",
            "url": "https://twitter.com/coinerr_err"
        },
        {
            "name": "telegram",
            "url": "https://t.me/coinerr_ERR"
        },
        {
            "name": "whitepaper",
            "url": "https://coinerr.io/papers/whitepaper.pdf"
        },
        {
            "name": "medium",
            "url": "https://coinerr.medium.com/"
        },
        {
            "name": "coinmarketcap",
            "url": "https://coinmarketcap.com/currencies/coinerr/"
        }
    ],
    "tags": [
        "defi"
    ]
 }
    

    
    ]
    
